{"box_data": [{"position": {"minX": 318.25, "minY": 242.625, "maxX": 346.75, "maxY": 271.0}, "class_id": 0, "box_caption": "1 0.929", "scores": {"class_score": 0.9287109375}, "domain": "pixel"}, {"position": {"minX": 193.625, "minY": 102.0625, "maxX": 221.875, "maxY": 130.0}, "class_id": 0, "box_caption": "1 0.928", "scores": {"class_score": 0.927734375}, "domain": "pixel"}, {"position": {"minX": 176.625, "minY": 373.0, "maxX": 205.875, "maxY": 402.5}, "class_id": 0, "box_caption": "1 0.928", "scores": {"class_score": 0.927734375}, "domain": "pixel"}, {"position": {"minX": 609.0, "minY": 262.25, "maxX": 640.0, "maxY": 292.75}, "class_id": 0, "box_caption": "1 0.922", "scores": {"class_score": 0.92236328125}, "domain": "pixel"}, {"position": {"minX": 464.25, "minY": 103.875, "maxX": 493.75, "maxY": 133.0}, "class_id": 0, "box_caption": "1 0.919", "scores": {"class_score": 0.9189453125}, "domain": "pixel"}, {"position": {"minX": 458.75, "minY": 399.5, "maxX": 488.25, "maxY": 428.0}, "class_id": 0, "box_caption": "1 0.918", "scores": {"class_score": 0.91845703125}, "domain": "pixel"}, {"position": {"minX": 55.5625, "minY": 236.75, "maxX": 83.6875, "maxY": 264.75}, "class_id": 0, "box_caption": "1 0.915", "scores": {"class_score": 0.9150390625}, "domain": "pixel"}, {"position": {"minX": 659.5, "minY": 488.75, "maxX": 671.5, "maxY": 514.5}, "class_id": 0, "box_caption": "1 0.007", "scores": {"class_score": 0.0068511962890625}, "domain": "pixel"}, {"position": {"minX": 602.0, "minY": 250.875, "maxX": 649.0, "maxY": 307.5}, "class_id": 0, "box_caption": "1 0.006", "scores": {"class_score": 0.0060272216796875}, "domain": "pixel"}, {"position": {"minX": 423.0, "minY": 102.875, "maxX": 826.0, "maxY": 436.5}, "class_id": 0, "box_caption": "1 0.005", "scores": {"class_score": 0.00524139404296875}, "domain": "pixel"}, {"position": {"minX": 246.75, "minY": -63.8125, "maxX": 680.0, "maxY": 281.0}, "class_id": 0, "box_caption": "1 0.003", "scores": {"class_score": 0.0034694671630859375}, "domain": "pixel"}, {"position": {"minX": 253.875, "minY": 224.625, "maxX": 672.0, "maxY": 569.5}, "class_id": 0, "box_caption": "1 0.003", "scores": {"class_score": 0.0030040740966796875}, "domain": "pixel"}, {"position": {"minX": -5.75, "minY": 227.875, "maxX": 420.75, "maxY": 570.5}, "class_id": 0, "box_caption": "1 0.003", "scores": {"class_score": 0.0026531219482421875}, "domain": "pixel"}, {"position": {"minX": 125.0, "minY": 95.75, "maxX": 546.0, "maxY": 446.25}, "class_id": 0, "box_caption": "1 0.002", "scores": {"class_score": 0.0024929046630859375}, "domain": "pixel"}, {"position": {"minX": 447.0, "minY": 81.0, "maxX": 507.0, "maxY": 156.375}, "class_id": 0, "box_caption": "1 0.002", "scores": {"class_score": 0.00243377685546875}, "domain": "pixel"}, {"position": {"minX": 658.5, "minY": 497.0, "maxX": 672.5, "maxY": 513.0}, "class_id": 0, "box_caption": "1 0.002", "scores": {"class_score": 0.0020999908447265625}, "domain": "pixel"}, {"position": {"minX": 444.0, "minY": 375.5, "maxX": 502.0, "maxY": 451.5}, "class_id": 0, "box_caption": "1 0.002", "scores": {"class_score": 0.0020198822021484375}, "domain": "pixel"}, {"position": {"minX": -13.875, "minY": -70.5, "maxX": 427.0, "maxY": 290.25}, "class_id": 0, "box_caption": "1 0.002", "scores": {"class_score": 0.002010345458984375}, "domain": "pixel"}, {"position": {"minX": 44.84375, "minY": 491.0, "maxX": 76.125, "maxY": 511.0}, "class_id": 0, "box_caption": "1 0.002", "scores": {"class_score": 0.001926422119140625}, "domain": "pixel"}, {"position": {"minX": 162.125, "minY": 349.0, "maxX": 225.375, "maxY": 430.0}, "class_id": 0, "box_caption": "1 0.002", "scores": {"class_score": 0.0018672943115234375}, "domain": "pixel"}, {"position": {"minX": -141.125, "minY": 57.25, "maxX": 298.0, "maxY": 421.75}, "class_id": 0, "box_caption": "1 0.002", "scores": {"class_score": 0.0017004013061523438}, "domain": "pixel"}, {"position": {"minX": 652.0, "minY": 490.5, "maxX": 672.0, "maxY": 515.0}, "class_id": 0, "box_caption": "1 0.002", "scores": {"class_score": 0.0016489028930664062}, "domain": "pixel"}, {"position": {"minX": 296.75, "minY": 212.25, "maxX": 371.75, "maxY": 306.75}, "class_id": 0, "box_caption": "1 0.001", "scores": {"class_score": 0.0012941360473632812}, "domain": "pixel"}, {"position": {"minX": 652.0, "minY": 499.0, "maxX": 671.0, "maxY": 513.0}, "class_id": 0, "box_caption": "1 0.001", "scores": {"class_score": 0.0011653900146484375}, "domain": "pixel"}], "class_labels": {"0": "1"}}