{"box_data": [{"position": {"minX": 214.625, "minY": 98.25, "maxX": 236.125, "maxY": 119.0}, "class_id": 0, "box_caption": "1 0.889", "scores": {"class_score": 0.88916015625}, "domain": "pixel"}, {"position": {"minX": 425.25, "minY": 126.75, "maxX": 447.75, "maxY": 148.5}, "class_id": 0, "box_caption": "1 0.881", "scores": {"class_score": 0.88134765625}, "domain": "pixel"}, {"position": {"minX": 309.25, "minY": 219.375, "maxX": 330.25, "maxY": 239.625}, "class_id": 0, "box_caption": "1 0.879", "scores": {"class_score": 0.87939453125}, "domain": "pixel"}, {"position": {"minX": 534.5, "minY": 42.84375, "maxX": 555.5, "maxY": 63.65625}, "class_id": 0, "box_caption": "1 0.845", "scores": {"class_score": 0.84521484375}, "domain": "pixel"}, {"position": {"minX": 423.0, "minY": 121.75, "maxX": 450.5, "maxY": 151.75}, "class_id": 0, "box_caption": "1 0.070", "scores": {"class_score": 0.06951904296875}, "domain": "pixel"}, {"position": {"minX": 533.0, "minY": 37.8125, "maxX": 558.0, "maxY": 67.8125}, "class_id": 0, "box_caption": "1 0.061", "scores": {"class_score": 0.060516357421875}, "domain": "pixel"}, {"position": {"minX": 213.75, "minY": 93.0, "maxX": 239.0, "maxY": 123.625}, "class_id": 0, "box_caption": "1 0.055", "scores": {"class_score": 0.055206298828125}, "domain": "pixel"}, {"position": {"minX": 309.75, "minY": 214.0, "maxX": 333.25, "maxY": 244.25}, "class_id": 0, "box_caption": "1 0.055", "scores": {"class_score": 0.055206298828125}, "domain": "pixel"}, {"position": {"minX": 655.5, "minY": 1.46875, "maxX": 669.5, "maxY": 18.375}, "class_id": 0, "box_caption": "1 0.014", "scores": {"class_score": 0.0135345458984375}, "domain": "pixel"}, {"position": {"minX": 645.5, "minY": 207.375, "maxX": 656.5, "maxY": 218.625}, "class_id": 0, "box_caption": "1 0.013", "scores": {"class_score": 0.013427734375}, "domain": "pixel"}, {"position": {"minX": 342.0, "minY": 13.390625, "maxX": 354.0, "maxY": 24.609375}, "class_id": 0, "box_caption": "1 0.010", "scores": {"class_score": 0.0101318359375}, "domain": "pixel"}, {"position": {"minX": 304.75, "minY": 220.5, "maxX": 323.25, "maxY": 238.0}, "class_id": 0, "box_caption": "1 0.010", "scores": {"class_score": 0.00971221923828125}, "domain": "pixel"}, {"position": {"minX": 639.5, "minY": 208.5, "maxX": 648.5, "maxY": 221.0}, "class_id": 0, "box_caption": "1 0.007", "scores": {"class_score": 0.0074615478515625}, "domain": "pixel"}, {"position": {"minX": 1.453125, "minY": 3.3515625, "maxX": 20.734375, "maxY": 19.375}, "class_id": 0, "box_caption": "1 0.005", "scores": {"class_score": 0.004627227783203125}, "domain": "pixel"}, {"position": {"minX": 1.875, "minY": 87.375, "maxX": 229.875, "maxY": 460.0}, "class_id": 0, "box_caption": "1 0.004", "scores": {"class_score": 0.004451751708984375}, "domain": "pixel"}, {"position": {"minX": 2.5234375, "minY": 491.75, "maxX": 19.3125, "maxY": 510.75}, "class_id": 0, "box_caption": "1 0.004", "scores": {"class_score": 0.004398345947265625}, "domain": "pixel"}, {"position": {"minX": 652.5, "minY": 490.5, "maxX": 671.5, "maxY": 511.5}, "class_id": 0, "box_caption": "1 0.004", "scores": {"class_score": 0.004329681396484375}, "domain": "pixel"}, {"position": {"minX": -19.9375, "minY": 180.0, "maxX": 254.25, "maxY": 341.0}, "class_id": 0, "box_caption": "1 0.004", "scores": {"class_score": 0.0041351318359375}, "domain": "pixel"}, {"position": {"minX": 658.5, "minY": 2.7734375, "maxX": 673.5, "maxY": 20.21875}, "class_id": 0, "box_caption": "1 0.004", "scores": {"class_score": 0.00400543212890625}, "domain": "pixel"}, {"position": {"minX": 26.203125, "minY": 242.625, "maxX": 45.5, "maxY": 264.0}, "class_id": 0, "box_caption": "1 0.004", "scores": {"class_score": 0.0038242340087890625}, "domain": "pixel"}, {"position": {"minX": 658.0, "minY": -1.1640625, "maxX": 675.0, "maxY": 15.6640625}, "class_id": 0, "box_caption": "1 0.003", "scores": {"class_score": 0.0034694671630859375}, "domain": "pixel"}, {"position": {"minX": 340.25, "minY": 14.421875, "maxX": 357.25, "maxY": 26.390625}, "class_id": 0, "box_caption": "1 0.003", "scores": {"class_score": 0.0032596588134765625}, "domain": "pixel"}, {"position": {"minX": 341.0, "minY": 11.2265625, "maxX": 354.0, "maxY": 28.84375}, "class_id": 0, "box_caption": "1 0.003", "scores": {"class_score": 0.0029811859130859375}, "domain": "pixel"}, {"position": {"minX": 349.25, "minY": 14.65625, "maxX": 360.75, "maxY": 25.625}, "class_id": 0, "box_caption": "1 0.003", "scores": {"class_score": 0.0026721954345703125}, "domain": "pixel"}, {"position": {"minX": 661.0, "minY": 0.7734375, "maxX": 671.0, "maxY": 13.8984375}, "class_id": 0, "box_caption": "1 0.003", "scores": {"class_score": 0.0025310516357421875}, "domain": "pixel"}, {"position": {"minX": 7.25, "minY": 174.0, "maxX": 207.75, "maxY": 387.0}, "class_id": 0, "box_caption": "1 0.003", "scores": {"class_score": 0.002521514892578125}, "domain": "pixel"}, {"position": {"minX": 652.0, "minY": -0.09375, "maxX": 671.0, "maxY": 14.25}, "class_id": 0, "box_caption": "1 0.002", "scores": {"class_score": 0.002414703369140625}, "domain": "pixel"}, {"position": {"minX": 207.75, "minY": 99.875, "maxX": 225.5, "maxY": 118.875}, "class_id": 0, "box_caption": "1 0.002", "scores": {"class_score": 0.0023975372314453125}, "domain": "pixel"}, {"position": {"minX": 81.75, "minY": 138.0, "maxX": 339.75, "maxY": 305.25}, "class_id": 0, "box_caption": "1 0.002", "scores": {"class_score": 0.00238800048828125}, "domain": "pixel"}, {"position": {"minX": 522.0, "minY": 43.9375, "maxX": 548.0, "maxY": 67.0}, "class_id": 0, "box_caption": "1 0.002", "scores": {"class_score": 0.0022602081298828125}, "domain": "pixel"}, {"position": {"minX": 655.5, "minY": 1.1328125, "maxX": 666.5, "maxY": 13.7890625}, "class_id": 0, "box_caption": "1 0.002", "scores": {"class_score": 0.002216339111328125}, "domain": "pixel"}, {"position": {"minX": 528.0, "minY": 44.78125, "maxX": 546.0, "maxY": 62.90625}, "class_id": 0, "box_caption": "1 0.002", "scores": {"class_score": 0.0021820068359375}, "domain": "pixel"}, {"position": {"minX": 346.5, "minY": 13.453125, "maxX": 363.0, "maxY": 26.359375}, "class_id": 0, "box_caption": "1 0.002", "scores": {"class_score": 0.0021820068359375}, "domain": "pixel"}, {"position": {"minX": 27.734375, "minY": 235.875, "maxX": 42.5, "maxY": 259.75}, "class_id": 0, "box_caption": "1 0.002", "scores": {"class_score": 0.002124786376953125}, "domain": "pixel"}, {"position": {"minX": 655.5, "minY": 8.1875, "maxX": 669.5, "maxY": 28.75}, "class_id": 0, "box_caption": "1 0.002", "scores": {"class_score": 0.0021152496337890625}, "domain": "pixel"}, {"position": {"minX": 655.0, "minY": 11.390625, "maxX": 674.0, "maxY": 26.265625}, "class_id": 0, "box_caption": "1 0.002", "scores": {"class_score": 0.0021076202392578125}, "domain": "pixel"}, {"position": {"minX": 33.875, "minY": -58.875, "maxX": 386.5, "maxY": 285.5}, "class_id": 0, "box_caption": "1 0.002", "scores": {"class_score": 0.0020904541015625}, "domain": "pixel"}, {"position": {"minX": 338.25, "minY": 5.16796875, "maxX": 357.75, "maxY": 19.578125}, "class_id": 0, "box_caption": "1 0.002", "scores": {"class_score": 0.00206756591796875}, "domain": "pixel"}, {"position": {"minX": 26.96875, "minY": 239.125, "maxX": 48.90625, "maxY": 255.625}, "class_id": 0, "box_caption": "1 0.002", "scores": {"class_score": 0.0020503997802734375}, "domain": "pixel"}, {"position": {"minX": -103.375, "minY": 55.625, "maxX": 583.0, "maxY": 377.5}, "class_id": 0, "box_caption": "1 0.002", "scores": {"class_score": 0.0020503997802734375}, "domain": "pixel"}, {"position": {"minX": -4.3203125, "minY": 2.46875, "maxX": 17.1875, "maxY": 20.09375}, "class_id": 0, "box_caption": "1 0.002", "scores": {"class_score": 0.002002716064453125}, "domain": "pixel"}, {"position": {"minX": 232.75, "minY": -29.125, "maxX": 641.0, "maxY": 258.5}, "class_id": 0, "box_caption": "1 0.002", "scores": {"class_score": 0.001964569091796875}, "domain": "pixel"}, {"position": {"minX": 203.5, "minY": 96.375, "maxX": 231.0, "maxY": 119.25}, "class_id": 0, "box_caption": "1 0.002", "scores": {"class_score": 0.001934051513671875}, "domain": "pixel"}, {"position": {"minX": -0.37890625, "minY": 3.8203125, "maxX": 12.078125, "maxY": 18.90625}, "class_id": 0, "box_caption": "1 0.002", "scores": {"class_score": 0.0018825531005859375}, "domain": "pixel"}, {"position": {"minX": 338.5, "minY": 1.375, "maxX": 353.5, "maxY": 22.90625}, "class_id": 0, "box_caption": "1 0.002", "scores": {"class_score": 0.0018463134765625}, "domain": "pixel"}, {"position": {"minX": 639.0, "minY": 202.875, "maxX": 648.0, "maxY": 214.375}, "class_id": 0, "box_caption": "1 0.002", "scores": {"class_score": 0.0018243789672851562}, "domain": "pixel"}, {"position": {"minX": 645.5, "minY": 201.875, "maxX": 657.5, "maxY": 213.625}, "class_id": 0, "box_caption": "1 0.002", "scores": {"class_score": 0.0018100738525390625}, "domain": "pixel"}, {"position": {"minX": 347.0, "minY": -106.625, "maxX": 717.0, "maxY": 205.875}, "class_id": 0, "box_caption": "1 0.002", "scores": {"class_score": 0.0017271041870117188}, "domain": "pixel"}, {"position": {"minX": 400.25, "minY": 86.1875, "maxX": 476.25, "maxY": 191.0}, "class_id": 0, "box_caption": "1 0.002", "scores": {"class_score": 0.001628875732421875}, "domain": "pixel"}, {"position": {"minX": 17.59375, "minY": 238.25, "maxX": 39.09375, "maxY": 254.25}, "class_id": 0, "box_caption": "1 0.002", "scores": {"class_score": 0.0015850067138671875}, "domain": "pixel"}, {"position": {"minX": 298.0, "minY": 218.125, "maxX": 324.0, "maxY": 242.875}, "class_id": 0, "box_caption": "1 0.002", "scores": {"class_score": 0.0015249252319335938}, "domain": "pixel"}, {"position": {"minX": 117.0, "minY": 75.125, "maxX": 495.0, "maxY": 409.5}, "class_id": 0, "box_caption": "1 0.002", "scores": {"class_score": 0.0015010833740234375}, "domain": "pixel"}, {"position": {"minX": 645.5, "minY": 0.6328125, "maxX": 665.5, "maxY": 14.8515625}, "class_id": 0, "box_caption": "1 0.001", "scores": {"class_score": 0.001495361328125}, "domain": "pixel"}, {"position": {"minX": 3.0625, "minY": -1.5, "maxX": 20.703125, "maxY": 16.65625}, "class_id": 0, "box_caption": "1 0.001", "scores": {"class_score": 0.0014896392822265625}, "domain": "pixel"}, {"position": {"minX": 16.046875, "minY": 243.625, "maxX": 40.5, "maxY": 261.25}, "class_id": 0, "box_caption": "1 0.001", "scores": {"class_score": 0.0014896392822265625}, "domain": "pixel"}, {"position": {"minX": 74.25, "minY": 446.75, "maxX": 147.75, "maxY": 493.25}, "class_id": 0, "box_caption": "1 0.001", "scores": {"class_score": 0.0014667510986328125}, "domain": "pixel"}, {"position": {"minX": 168.0, "minY": 51.59375, "maxX": 275.0, "maxY": 170.5}, "class_id": 0, "box_caption": "1 0.001", "scores": {"class_score": 0.001438140869140625}, "domain": "pixel"}, {"position": {"minX": 349.5, "minY": 15.0625, "maxX": 367.0, "maxY": 26.6875}, "class_id": 0, "box_caption": "1 0.001", "scores": {"class_score": 0.0014209747314453125}, "domain": "pixel"}, {"position": {"minX": 533.5, "minY": 288.75, "maxX": 547.5, "maxY": 302.75}, "class_id": 0, "box_caption": "1 0.001", "scores": {"class_score": 0.0014209747314453125}, "domain": "pixel"}, {"position": {"minX": 636.0, "minY": 203.625, "maxX": 650.0, "maxY": 213.625}, "class_id": 0, "box_caption": "1 0.001", "scores": {"class_score": 0.0014162063598632812}, "domain": "pixel"}, {"position": {"minX": 381.5, "minY": 59.4375, "maxX": 482.5, "maxY": 209.75}, "class_id": 0, "box_caption": "1 0.001", "scores": {"class_score": 0.0014104843139648438}, "domain": "pixel"}, {"position": {"minX": 349.5, "minY": 11.046875, "maxX": 362.5, "maxY": 29.921875}, "class_id": 0, "box_caption": "1 0.001", "scores": {"class_score": 0.0014047622680664062}, "domain": "pixel"}, {"position": {"minX": 19.953125, "minY": 228.0, "maxX": 38.9375, "maxY": 248.75}, "class_id": 0, "box_caption": "1 0.001", "scores": {"class_score": 0.0013942718505859375}, "domain": "pixel"}, {"position": {"minX": 124.0, "minY": 457.0, "maxX": 144.25, "maxY": 478.0}, "class_id": 0, "box_caption": "1 0.001", "scores": {"class_score": 0.0013885498046875}, "domain": "pixel"}, {"position": {"minX": -105.125, "minY": 158.625, "maxX": 261.5, "maxY": 381.0}, "class_id": 0, "box_caption": "1 0.001", "scores": {"class_score": 0.0013408660888671875}, "domain": "pixel"}, {"position": {"minX": 493.5, "minY": -7.1875, "maxX": 599.5, "maxY": 113.1875}, "class_id": 0, "box_caption": "1 0.001", "scores": {"class_score": 0.0012998580932617188}, "domain": "pixel"}, {"position": {"minX": 20.828125, "minY": 237.125, "maxX": 34.0, "maxY": 255.375}, "class_id": 0, "box_caption": "1 0.001", "scores": {"class_score": 0.0012941360473632812}, "domain": "pixel"}, {"position": {"minX": 32.5, "minY": 199.875, "maxX": 247.75, "maxY": 301.25}, "class_id": 0, "box_caption": "1 0.001", "scores": {"class_score": 0.0012645721435546875}, "domain": "pixel"}, {"position": {"minX": 342.25, "minY": 7.17578125, "maxX": 354.75, "maxY": 20.15625}, "class_id": 0, "box_caption": "1 0.001", "scores": {"class_score": 0.0012598037719726562}, "domain": "pixel"}, {"position": {"minX": 72.75, "minY": 204.5, "maxX": 275.0, "maxY": 261.75}, "class_id": 0, "box_caption": "1 0.001", "scores": {"class_score": 0.0012445449829101562}, "domain": "pixel"}, {"position": {"minX": 26.328125, "minY": 225.25, "maxX": 42.4375, "maxY": 250.75}, "class_id": 0, "box_caption": "1 0.001", "scores": {"class_score": 0.0012350082397460938}, "domain": "pixel"}, {"position": {"minX": 20.890625, "minY": 243.5, "maxX": 34.6875, "maxY": 261.75}, "class_id": 0, "box_caption": "1 0.001", "scores": {"class_score": 0.0012350082397460938}, "domain": "pixel"}, {"position": {"minX": 647.0, "minY": -3.8203125, "maxX": 661.0, "maxY": 19.1875}, "class_id": 0, "box_caption": "1 0.001", "scores": {"class_score": 0.001220703125}, "domain": "pixel"}, {"position": {"minX": 531.0, "minY": 290.25, "maxX": 547.0, "maxY": 299.75}, "class_id": 0, "box_caption": "1 0.001", "scores": {"class_score": 0.0011882781982421875}, "domain": "pixel"}, {"position": {"minX": 98.0, "minY": 210.25, "maxX": 119.75, "maxY": 228.75}, "class_id": 0, "box_caption": "1 0.001", "scores": {"class_score": 0.001178741455078125}, "domain": "pixel"}, {"position": {"minX": -3.734375, "minY": 228.5, "maxX": 45.5625, "maxY": 259.75}, "class_id": 0, "box_caption": "1 0.001", "scores": {"class_score": 0.0011653900146484375}, "domain": "pixel"}, {"position": {"minX": 446.0, "minY": 361.0, "maxX": 460.0, "maxY": 374.5}, "class_id": 0, "box_caption": "1 0.001", "scores": {"class_score": 0.0011472702026367188}, "domain": "pixel"}, {"position": {"minX": 5.0, "minY": 0.32421875, "maxX": 15.9375, "maxY": 14.65625}, "class_id": 0, "box_caption": "1 0.001", "scores": {"class_score": 0.0011472702026367188}, "domain": "pixel"}, {"position": {"minX": 348.5, "minY": 4.5625, "maxX": 369.0, "maxY": 18.78125}, "class_id": 0, "box_caption": "1 0.001", "scores": {"class_score": 0.0011377334594726562}, "domain": "pixel"}, {"position": {"minX": 80.625, "minY": 225.0, "maxX": 105.75, "maxY": 244.25}, "class_id": 0, "box_caption": "1 0.001", "scores": {"class_score": 0.0011377334594726562}, "domain": "pixel"}, {"position": {"minX": 94.8125, "minY": 347.25, "maxX": 147.125, "maxY": 406.75}, "class_id": 0, "box_caption": "1 0.001", "scores": {"class_score": 0.0011339187622070312}, "domain": "pixel"}, {"position": {"minX": 355.5, "minY": 12.453125, "maxX": 369.0, "maxY": 28.265625}, "class_id": 0, "box_caption": "1 0.001", "scores": {"class_score": 0.001129150390625}, "domain": "pixel"}, {"position": {"minX": 648.5, "minY": 2.75390625, "maxX": 662.5, "maxY": 18.625}, "class_id": 0, "box_caption": "1 0.001", "scores": {"class_score": 0.0011243820190429688}, "domain": "pixel"}, {"position": {"minX": 311.25, "minY": 416.0, "maxX": 372.75, "maxY": 490.5}, "class_id": 0, "box_caption": "1 0.001", "scores": {"class_score": 0.0011205673217773438}, "domain": "pixel"}, {"position": {"minX": 446.5, "minY": 360.0, "maxX": 455.5, "maxY": 375.0}, "class_id": 0, "box_caption": "1 0.001", "scores": {"class_score": 0.0011157989501953125}, "domain": "pixel"}, {"position": {"minX": 348.75, "minY": 0.953125, "maxX": 364.25, "maxY": 22.359375}, "class_id": 0, "box_caption": "1 0.001", "scores": {"class_score": 0.0010986328125}, "domain": "pixel"}, {"position": {"minX": 143.625, "minY": 133.5, "maxX": 217.375, "maxY": 295.75}, "class_id": 0, "box_caption": "1 0.001", "scores": {"class_score": 0.001094818115234375}, "domain": "pixel"}, {"position": {"minX": 91.375, "minY": 187.0, "maxX": 169.375, "maxY": 330.5}, "class_id": 0, "box_caption": "1 0.001", "scores": {"class_score": 0.0010900497436523438}, "domain": "pixel"}, {"position": {"minX": 114.0625, "minY": 190.5, "maxX": 131.0, "maxY": 214.0}, "class_id": 0, "box_caption": "1 0.001", "scores": {"class_score": 0.0010652542114257812}, "domain": "pixel"}, {"position": {"minX": 322.25, "minY": 288.25, "maxX": 385.75, "maxY": 348.75}, "class_id": 0, "box_caption": "1 0.001", "scores": {"class_score": 0.0010652542114257812}, "domain": "pixel"}, {"position": {"minX": 112.5, "minY": 194.0, "maxX": 134.875, "maxY": 210.5}, "class_id": 0, "box_caption": "1 0.001", "scores": {"class_score": 0.0010528564453125}, "domain": "pixel"}, {"position": {"minX": 25.53125, "minY": 228.375, "maxX": 47.65625, "maxY": 246.375}, "class_id": 0, "box_caption": "1 0.001", "scores": {"class_score": 0.0010528564453125}, "domain": "pixel"}, {"position": {"minX": 245.5, "minY": 416.5, "maxX": 304.0, "maxY": 493.0}, "class_id": 0, "box_caption": "1 0.001", "scores": {"class_score": 0.0010480880737304688}, "domain": "pixel"}, {"position": {"minX": 31.421875, "minY": 244.0, "maxX": 51.9375, "maxY": 263.0}, "class_id": 0, "box_caption": "1 0.001", "scores": {"class_score": 0.0010404586791992188}, "domain": "pixel"}, {"position": {"minX": 125.0, "minY": 458.5, "maxX": 137.75, "maxY": 477.0}, "class_id": 0, "box_caption": "1 0.001", "scores": {"class_score": 0.0010366439819335938}, "domain": "pixel"}, {"position": {"minX": 81.75, "minY": 220.5, "maxX": 101.375, "maxY": 248.0}, "class_id": 0, "box_caption": "1 0.001", "scores": {"class_score": 0.0010366439819335938}, "domain": "pixel"}, {"position": {"minX": 11.453125, "minY": 2.3125, "maxX": 26.890625, "maxY": 20.09375}, "class_id": 0, "box_caption": "1 0.001", "scores": {"class_score": 0.0010318756103515625}, "domain": "pixel"}, {"position": {"minX": 413.0, "minY": 123.1875, "maxX": 446.5, "maxY": 153.875}, "class_id": 0, "box_caption": "1 0.001", "scores": {"class_score": 0.0010318756103515625}, "domain": "pixel"}, {"position": {"minX": 5.5859375, "minY": 44.6875, "maxX": 21.375, "maxY": 61.75}, "class_id": 0, "box_caption": "1 0.001", "scores": {"class_score": 0.0010280609130859375}, "domain": "pixel"}, {"position": {"minX": 355.75, "minY": 301.5, "maxX": 386.25, "maxY": 334.0}, "class_id": 0, "box_caption": "1 0.001", "scores": {"class_score": 0.0010242462158203125}, "domain": "pixel"}, {"position": {"minX": 320.25, "minY": 46.375, "maxX": 337.75, "maxY": 69.375}, "class_id": 0, "box_caption": "1 0.001", "scores": {"class_score": 0.0010204315185546875}, "domain": "pixel"}, {"position": {"minX": -13.65625, "minY": 385.5, "maxX": 55.28125, "maxY": 429.5}, "class_id": 0, "box_caption": "1 0.001", "scores": {"class_score": 0.0010166168212890625}, "domain": "pixel"}, {"position": {"minX": -80.125, "minY": 306.5, "maxX": 290.5, "maxY": 618.5}, "class_id": 0, "box_caption": "1 0.001", "scores": {"class_score": 0.0010080337524414062}, "domain": "pixel"}, {"position": {"minX": 356.25, "minY": 14.4140625, "maxX": 367.75, "maxY": 25.46875}, "class_id": 0, "box_caption": "1 0.001", "scores": {"class_score": 0.0010042190551757812}, "domain": "pixel"}], "class_labels": {"0": "1"}}